{
  "$schema": "https://biomejs.dev/schemas/1.8.3/schema.json",
  "files": {
    "ignore": [
      "node_modules",
      "dist",
      ".next",
      "target",
      "coverage",
      ".turbo"
    ]
  },
  "formatter": {
    "enabled": true,
    "formatWithErrors": false,
    "indentStyle": "space",
    "indentWidth": 2,
    "lineWidth": 100,
    "lineEnding": "lf"
  },
  "linter": {
    "enabled": true,
    "rules": {
      "recommended": true,
      "complexity": {
        "noExcessiveCognitiveComplexity": "warn",
        "noUselessConstructor": "error"
      },
      "correctness": {
        "noUnusedVariables": "error",
        "useExhaustiveDependencies": "warn"
      },
      "style": {
        "noNegationElse": "error",
        "useShorthandFunctionType": "error"
      },
      "suspicious": {
        "noArrayIndexKey": "warn",
        "noConsoleLog": "warn",
        "noDebugger": "error",
        "noEmptyBlockStatements": "error"
      },
      "nursery": {
        "useSortedClasses": "error"
      }
    }
  },
  "javascript": {
    "formatter": {
      "jsxQuoteStyle": "double",
      "quoteProperties": "asNeeded",
      "trailingCommas": "es5",
      "semicolons": "always",
      "arrowParentheses": "always",
      "bracketSpacing": true,
      "bracketSameLine": false,
      "quoteStyle": "double",
      "attributePosition": "auto"
    }
  },
  "typescript": {
    "formatter": {
      "jsxQuoteStyle": "double",
      "quoteProperties": "asNeeded",
      "trailingCommas": "es5",
      "semicolons": "always",
      "arrowParentheses": "always",
      "bracketSpacing": true,
      "bracketSameLine": false,
      "quoteStyle": "double",
      "attributePosition": "auto"
    }
  },
  "json": {
    "formatter": {
      "indentStyle": "space",
      "indentWidth": 2,
      "trailingCommas": "none"
    }
  }
}
